LICENSE
README.rst
setup.py
test/test_hetero_batch_graph.py
tf_geometric/__init__.py
tf_geometric.egg-info/PKG-INFO
tf_geometric.egg-info/SOURCES.txt
tf_geometric.egg-info/dependency_links.txt
tf_geometric.egg-info/requires.txt
tf_geometric.egg-info/top_level.txt
tf_geometric/data/__init__.py
tf_geometric/data/dataset.py
tf_geometric/data/graph.py
tf_geometric/datasets/__init__.py
tf_geometric/datasets/abnormal.py
tf_geometric/datasets/amazon_electronics.py
tf_geometric/datasets/blog_catalog.py
tf_geometric/datasets/coauthor.py
tf_geometric/datasets/csr_npz.py
tf_geometric/datasets/hgb.py
tf_geometric/datasets/model_net.py
tf_geometric/datasets/nars_academic.py
tf_geometric/datasets/ogb.py
tf_geometric/datasets/planetoid.py
tf_geometric/datasets/ppi.py
tf_geometric/datasets/reddit.py
tf_geometric/datasets/synthetic.py
tf_geometric/datasets/tu.py
tf_geometric/layers/__init__.py
tf_geometric/layers/conv/__init__.py
tf_geometric/layers/conv/appnp.py
tf_geometric/layers/conv/chebynet.py
tf_geometric/layers/conv/gat.py
tf_geometric/layers/conv/gcn.py
tf_geometric/layers/conv/gin.py
tf_geometric/layers/conv/graph_sage.py
tf_geometric/layers/conv/le_conv.py
tf_geometric/layers/conv/sgc.py
tf_geometric/layers/conv/ssgc.py
tf_geometric/layers/conv/tagcn.py
tf_geometric/layers/kernel/__init__.py
tf_geometric/layers/kernel/map_reduce.py
tf_geometric/layers/pool/__init__.py
tf_geometric/layers/pool/asap.py
tf_geometric/layers/pool/common_pool.py
tf_geometric/layers/pool/diff_pool.py
tf_geometric/layers/pool/min_cut_pool.py
tf_geometric/layers/pool/sag_pool.py
tf_geometric/layers/pool/set2set.py
tf_geometric/layers/pool/sort_pool.py
tf_geometric/layers/sampling/__init__.py
tf_geometric/layers/sampling/drop_edge.py
tf_geometric/nn/__init__.py
tf_geometric/nn/conv/__init__.py
tf_geometric/nn/conv/appnp.py
tf_geometric/nn/conv/chebynet.py
tf_geometric/nn/conv/gat.py
tf_geometric/nn/conv/gcn.py
tf_geometric/nn/conv/gin.py
tf_geometric/nn/conv/graph_sage.py
tf_geometric/nn/conv/le_conv.py
tf_geometric/nn/conv/sgc.py
tf_geometric/nn/conv/ssgc.py
tf_geometric/nn/conv/tagcn.py
tf_geometric/nn/kernel/__init__.py
tf_geometric/nn/kernel/map_reduce.py
