Metadata-Version: 2.1
Name: tf_geometric
Version: 0.1.7
Summary: Efficient and Friendly Graph Neural Network Library for TensorFlow 1.x and 2.x.
Home-page: https://github.com/CrawlScript/tf_geometric
Author: Jun Hu
Author-email: hujunxianligong@gmail.com
License: GNU General Public License v3.0 (See LICENSE)
Requires-Python: >3.5.0
License-File: LICENSE
Requires-Dist: tf_sparse>=0.0.17
Requires-Dist: numpy>=1.17.4
Requires-Dist: networkx>=2.1
Requires-Dist: scipy>=1.1.0
Requires-Dist: scikit-learn>=0.22
Requires-Dist: ogb_lite>=0.0.3
Requires-Dist: tqdm
Provides-Extra: tf1-cpu
Requires-Dist: tensorflow<2.0.0,>=1.15.0; extra == "tf1-cpu"
Provides-Extra: tf1-gpu
Requires-Dist: tensorflow-gpu<2.0.0,>=1.15.0; extra == "tf1-gpu"
Provides-Extra: tf2-cpu
Requires-Dist: tensorflow>=2.4.0; extra == "tf2-cpu"
Provides-Extra: tf2-gpu
Requires-Dist: tensorflow>=2.4.0; extra == "tf2-gpu"
